daka.py
samba.py
daka-0.0.0.dist-info/METADATA
daka-0.0.0.dist-info/RECORD
daka-0.0.0.dist-info/WHEEL
daka-0.0.0.dist-info/top_level.txt
