Metadata-Version: 2.1
Name: daka
Version: 0.0.0
Summary: A very small PaaS to do git push app deployments to your own servers, similar to Heroku
Home-page: https://github.com/mardix/daka/
Author: Mardix
Author-email: mcx2082@gmail.com
License: MIT
Download-URL: https://github.com/mardix/daka/tarball/master
Keywords: deploy,daka,flask,gunicorn,django,workers,heroku,firebase,dokku,paas,assembly,piku
Platform: any
Classifier: Environment :: Web Environment
Classifier: Intended Audience :: Developers
Classifier: License :: OSI Approved :: BSD License
Classifier: Operating System :: OS Independent
Classifier: Programming Language :: Python
Classifier: Programming Language :: Python :: 2
Classifier: Programming Language :: Python :: 2.6
Classifier: Programming Language :: Python :: 2.7
Classifier: Programming Language :: Python :: 3
Classifier: Programming Language :: Python :: 3.3
Classifier: Programming Language :: Python :: 3.4
Classifier: Topic :: Internet :: WWW/HTTP :: Dynamic Content
Classifier: Topic :: Software Development :: Libraries :: Python Modules
Requires-Dist: virtualenv
Requires-Dist: uwsgi
Requires-Dist: click
